p3mail/__init__.py
p3mail/consts.py
p3mail/p3mail.py
p3mail-0.1.1.dist-info/LICENSE.txt
p3mail-0.1.1.dist-info/METADATA
p3mail-0.1.1.dist-info/RECORD
p3mail-0.1.1.dist-info/WHEEL
p3mail-0.1.1.dist-info/entry_points.txt
p3mail-0.1.1.dist-info/top_level.txt
