Metadata-Version: 2.1
Name: p3mail
Version: 0.1.1
Summary: a Pathetic Python Pipe Mail sender to send terminal outputs by mail
Home-page: https://github.com/krypty/p3mail
Author: Gary Marigliano
Author-email: gary-pypi@marigliano.ch
License: UNKNOWN
Keywords: mail pipe stdin
Platform: UNKNOWN
Classifier: License :: OSI Approved :: GNU General Public License v3 (GPLv3)
Classifier: Programming Language :: Python :: 3.5
Classifier: Topic :: Utilities
Requires-Python: >=3.5
